openudm/CellularModel.py
openudm/DevZones.py
openudm/MultiCriteriaEval.py
openudm/RasterToolkit.py
openudm/_CellularModel.cp38-win_amd64.pyd
openudm/_DevZones.cp38-win_amd64.pyd
openudm/_MultiCriteriaEval.cp38-win_amd64.pyd
openudm/_RasterToolkit.cp38-win_amd64.pyd
openudm/__init__.py
openudm/__main__.py
openudm-1.0.0.dist-info/LICENSE
openudm-1.0.0.dist-info/METADATA
openudm-1.0.0.dist-info/WHEEL
openudm-1.0.0.dist-info/top_level.txt
openudm-1.0.0.dist-info/RECORD
