Metadata-Version: 2.1
Name: openudm
Version: 1.0.0
Summary: Urban Development Model
Home-page: UNKNOWN
Author: James Virgo
Author-email: UNKNOWN
License: UNKNOWN
Platform: UNKNOWN
